oodocument/__init__.py
oodocument/oodocument.py
oodocument/test.py
oodocument-0.0.8.dist-info/LICENSE
oodocument-0.0.8.dist-info/METADATA
oodocument-0.0.8.dist-info/WHEEL
oodocument-0.0.8.dist-info/top_level.txt
oodocument-0.0.8.dist-info/RECORD
