Metadata-Version: 2.1
Name: oodocument
Version: 0.0.8
Summary: Basic tasks to convert and replace files using uno api
Home-page: https://github.com/Cambalab/oodocument
Author: José Luis Di Biase
Author-email: josx@camba.coop
License: UNKNOWN
Platform: UNKNOWN
Classifier: Programming Language :: Python :: 3
Classifier: License :: OSI Approved :: GNU General Public License v3 (GPLv3)
Classifier: Operating System :: OS Independent
Classifier: Topic :: Office/Business :: Office Suites
Requires-Python: >=3.6
